zytlib/__init__.py
zytlib/table.py
zytlib/vector.py
zytlib/container/__init__.py
zytlib/container/sequence.py
zytlib/container/table.py
zytlib/container/torch_table.py
zytlib/container/vector.py
zytlib/deprecated/__init__.py
zytlib/deprecated/_test_curses.py
zytlib/deprecated/terminal.py
zytlib/inout/__init__.py
zytlib/inout/filemanager.py
zytlib/inout/logging.py
zytlib/nstools/__init__.py
zytlib/nstools/torch_utils.py
zytlib/nstools/vector_utils.py
zytlib/utils/__init__.py
zytlib/utils/classfunc.py
zytlib/utils/strtools.py
zytlib/utils/timing.py
zytlib/utils/touch.py
zytlib/utils/utils.py
zytlib/utils/wrapper.py
zytlib/utils/wrapper_plus.py
zytlib/visual/__init__.py
zytlib/visual/animation.py
zytlib/visual/debugger.py
zytlib/visual/display.py
zytlib/visual/plot.py
zytlib/visual/progress.py
zytlib-0.3.350.dist-info/METADATA
zytlib-0.3.350.dist-info/WHEEL
zytlib-0.3.350.dist-info/top_level.txt
zytlib-0.3.350.dist-info/RECORD
