Metadata-Version: 2.1
Name: zytlib
Version: 0.3.350
Summary: This is A foundamental package containing some basic self-designed functions and types for Project PyCTLib. 
Home-page: https://github.com/Bertie97/pyctlib/tree/main/pyctlib
Author: All contributors of PyCTLib
Author-email: zytfdu@icloud.com
License: MIT Licence
Keywords: pip,zytlib
Platform: any
Requires-Dist: pyoverload (==1.1.27)
Requires-Dist: rapidfuzz
Requires-Dist: numpy
Requires-Dist: wrapt-timeout-decorator
Requires-Dist: notion
Requires-Dist: pycamia
Requires-Dist: matplotlib
